hydrocnhs/Config_logging.yaml
hydrocnhs/__init__.py
hydrocnhs/abm.py
hydrocnhs/abm_script.py
hydrocnhs/data_collector.py
hydrocnhs/hydrocnhs.py
hydrocnhs/indicators.py
hydrocnhs/model_builder.py
hydrocnhs/routing.py
hydrocnhs/sediment.py
hydrocnhs/util.py
hydrocnhs/visual.py
hydrocnhs/calibration/__init__.py
hydrocnhs/calibration/convertor.py
hydrocnhs/calibration/ga_deap.py
hydrocnhs/rainfall_runoff_model/__init__.py
hydrocnhs/rainfall_runoff_model/abcd.py
hydrocnhs/rainfall_runoff_model/gwlf.py
hydrocnhs/rainfall_runoff_model/pet_hamon.py
hydrocnhs-1.2.0.dist-info/METADATA
hydrocnhs-1.2.0.dist-info/WHEEL
hydrocnhs-1.2.0.dist-info/licenses/LICENSE
hydrocnhs-1.2.0.dist-info/RECORD
