Metadata-Version: 2.3
Name: hydrocnhs
Version: 1.2.0
Summary: A Python Package of Hydrological Model for Coupled Natural–Human Systems
Author-email: Chung-Yi Lin <philip928lin@gmail.com>
License: BSD 3-Clause License
License-File: LICENSE
Requires-Dist: deap
Requires-Dist: joblib
Requires-Dist: matplotlib
Requires-Dist: numpy
Requires-Dist: pandas
Requires-Dist: pyyaml
Requires-Dist: ruamel-yaml
Requires-Dist: scikit-learn
Requires-Dist: scipy
Requires-Dist: tqdm
Provides-Extra: dev
Requires-Dist: ipython; extra == 'dev'
Provides-Extra: lint
Requires-Dist: pre-commit>=2.20.0; extra == 'lint'
